handlescreenshots/README.MD
handlescreenshots/__init__.py
handlescreenshots/requirements.txt
handlescreenshots/thirdparty.json
handlescreenshots-0.10.dist-info/LICENSE.rst
handlescreenshots-0.10.dist-info/METADATA
handlescreenshots-0.10.dist-info/WHEEL
handlescreenshots-0.10.dist-info/top_level.txt
handlescreenshots-0.10.dist-info/RECORD
