Metadata-Version: 2.1
Name: handlescreenshots
Version: 0.10
Summary: Fast screenshots of (background) windows with, includes a find_window method
Home-page: https://github.com/hansalemaos/handlescreenshots
Author: Johannes Fischer
Author-email: aulasparticularesdealemaosp@gmail.com
License: MIT
Keywords: screenshots,hwnd
Classifier: Development Status :: 4 - Beta
Classifier: Programming Language :: Python :: 3 :: Only
Classifier: Programming Language :: Python :: 3.10
Classifier: Topic :: Software Development :: Libraries :: Python Modules
Classifier: Topic :: Utilities
License-File: LICENSE.rst
Requires-Dist: appshwnd
Requires-Dist: numpy
Requires-Dist: pywin32
